{"comments": 30, "commits": 1619, "followers": 64, "issues": 40, "languages": {"C++": 2705, "CSS": 52631, "HTML": 58485739, "Java": 1371955, "JavaScript": 131538, "Jupyter Notebook": 1405783, "Kotlin": 3089945, "Python": 104999, "Shell": 12514, "Text": 422, "TypeScript": 13140}, "organizations": 6, "prs": {"additions": 52809, "commits": 704, "deletions": 60233, "merged": 130, "open": 4, "total": 145}, "pullRequestReviews": 60, "repos": {"count": 80, "diskUsage": 380450, "forks": 300, "issues": 363, "pullRequests": 238, "releases": 32, "stars": 2182, "watches": 167}, "timestamp": 1669094495}